MANIFEST.in
README.txt
setup.cfg
setup.py
docs/HISTORY.txt
docs/INSTALL.txt
docs/LICENSE.txt
docs/data1.txt
docs/data2.txt
jalon/__init__.py
jalon.wims.egg-info/PKG-INFO
jalon.wims.egg-info/SOURCES.txt
jalon.wims.egg-info/dependency_links.txt
jalon.wims.egg-info/entry_points.txt
jalon.wims.egg-info/namespace_packages.txt
jalon.wims.egg-info/not-zip-safe
jalon.wims.egg-info/requires.txt
jalon.wims.egg-info/top_level.txt
jalon/wims/__init__.py
jalon/wims/configure.zcml
jalon/wims/exportimport.py
jalon/wims/profiles.zcml
jalon/wims/setuphandlers.py
jalon/wims/tests.py
jalon/wims/utility.py
jalon/wims/browser/__init__.py
jalon/wims/browser/browser.py
jalon/wims/browser/configure.zcml
jalon/wims/browser/controlpanel.py
jalon/wims/browser/images/wims_icon.gif
jalon/wims/browser/interfaces/__init__.py
jalon/wims/browser/interfaces/browser.py
jalon/wims/browser/interfaces/controlpanel.py
jalon/wims/interfaces/__init__.py
jalon/wims/interfaces/utility.py
jalon/wims/profiles/default/componentregistry.xml
jalon/wims/profiles/default/controlpanel.xml
jalon/wims/profiles/default/metadata.xml
jalon/wims/profiles/default/portal-connect.txt
jalon/wims/profiles/default/toolset.xml
jalon/wims/profiles/default/wims.xml