Metadata-Version: 1.1
Name: jalon.wims
Version: 2.2.4
Summary: Wims connector
Home-page: http://opensource.unice.fr
Author: Olivier Bado, Bordonado Christophe - Université Nice Sophia Antipolis (uns) Service TICE
Author-email: tice@unice.fr
License: UNKNOWN
Platform: UNKNOWN
Classifier: Framework :: Plone
Classifier: Programming Language :: Python
